access_mopper/__init__.py
access_mopper/_config.py
access_mopper/_version.py
access_mopper/atmosphere.py
access_mopper/base.py
access_mopper/batch_cmoriser.py
access_mopper/defaults.py
access_mopper/driver.py
access_mopper/ocean.py
access_mopper/ocean_supergrid.py
access_mopper/tracking.py
access_mopper/utilities.py
access_mopper/vocabulary_processors.py
access_mopper/dashboard/__init__.py
access_mopper/dashboard/cmor_dashboard.py
access_mopper/derivations/__init__.py
access_mopper/derivations/calc_atmos.py
access_mopper/derivations/calc_land.py
access_mopper/derivations/calc_utils.py
access_mopper/examples/batch_config.yml
access_mopper/examples/show_config.py
access_mopper/executors/pbs_scheduler.py
access_mopper/mappings/Mappings_CMIP6_Amon.json
access_mopper/mappings/Mappings_CMIP6_CFday.json
access_mopper/mappings/Mappings_CMIP6_Eday.json
access_mopper/mappings/Mappings_CMIP6_Emon.json
access_mopper/mappings/Mappings_CMIP6_Lmon.json
access_mopper/mappings/Mappings_CMIP6_Omon.json
access_mopper/mappings/Mappings_CMIP6_day.json
access_mopper/mappings/Mappings_CMIP6_fx.json
access_mopper/mappings/Mappings_OM3_Ofx.json
access_mopper/mappings/Mappings_OM3_Omon.json
access_mopper/vocabularies/cmip6_cmor_tables/LICENSE.md
access_mopper/vocabularies/cmip6_cmor_tables/README.md
access_mopper/vocabularies/cmip6_cmor_tables/CMIP6_CVs/CITATION.cff
access_mopper/vocabularies/cmip6_cmor_tables/CMIP6_CVs/CMIP6_DRS.json
access_mopper/vocabularies/cmip6_cmor_tables/CMIP6_CVs/CMIP6_activity_id.json
access_mopper/vocabularies/cmip6_cmor_tables/CMIP6_CVs/CMIP6_experiment_id.json
access_mopper/vocabularies/cmip6_cmor_tables/CMIP6_CVs/CMIP6_frequency.json
access_mopper/vocabularies/cmip6_cmor_tables/CMIP6_CVs/CMIP6_grid_label.json
access_mopper/vocabularies/cmip6_cmor_tables/CMIP6_CVs/CMIP6_institution_id.json
access_mopper/vocabularies/cmip6_cmor_tables/CMIP6_CVs/CMIP6_license.json
access_mopper/vocabularies/cmip6_cmor_tables/CMIP6_CVs/CMIP6_nominal_resolution.json
access_mopper-2.3.0a24.dist-info/licenses/LICENCE.txt
access_mopper-2.3.0a24.dist-info/METADATA
access_mopper-2.3.0a24.dist-info/WHEEL
access_mopper-2.3.0a24.dist-info/entry_points.txt
access_mopper-2.3.0a24.dist-info/top_level.txt
access_mopper-2.3.0a24.dist-info/RECORD
